bin/__init__.py
bin/main.py
common/__init__.py
common/ai.py
aiop-0.0.5.dist-info/LICENSE
aiop-0.0.5.dist-info/METADATA
aiop-0.0.5.dist-info/WHEEL
aiop-0.0.5.dist-info/entry_points.txt
aiop-0.0.5.dist-info/top_level.txt
aiop-0.0.5.dist-info/RECORD
