Metadata-Version: 2.1
Name: aiop
Version: 0.0.5
Summary: AI toolset
Home-page: https://github.com/Alndaly/aiop
Author: Kinda Hall
Author-email: 1142704468@qq.com
Maintainer: Kinda Hall
Maintainer-email: 1142704468@qq.com
License: Copyright (c) 2024 Kinda Hall
Keywords: pip,tools
Platform: any
Requires-Python: >=3.10
License-File: LICENSE
Requires-Dist: typer
Requires-Dist: httpx
Requires-Dist: tqdm
